notion_api_py/__init__.py
notion_api_py/notion_api.py
notion_api_py/notion_collection_view_filter.py
notion_api_py/notion_databases.py
notion_api_py/notion_endpoints.py
notion_api_py/notion_filter.py
notion_api_py/notion_page.py
notion_api_py/notion_properties.py
notion_api_py/notion_relations.py
notion_api_py-1.0.2.dist-info/LICENSE
notion_api_py-1.0.2.dist-info/WHEEL
notion_api_py-1.0.2.dist-info/METADATA
notion_api_py-1.0.2.dist-info/RECORD
