Metadata-Version: 2.1
Name: notion-api-py
Version: 1.0.2
Summary: A wrapper around notion api allowing you to create objects for your databases/pages and easily perform add/update/delete/filter operations in a more readable way
Home-page: https://github.com/sunnydsouza/notion-api-py
License: MIT
Author: sunnydsouza
Author-email: dsouzasunny1436@gmail.com
Requires-Python: >=3.6,<4.0
Classifier: License :: OSI Approved :: MIT License
Classifier: Programming Language :: Python :: 3
Classifier: Programming Language :: Python :: 3.10
Classifier: Programming Language :: Python :: 3.6
Classifier: Programming Language :: Python :: 3.7
Classifier: Programming Language :: Python :: 3.8
Classifier: Programming Language :: Python :: 3.9
Requires-Dist: requests (>=2.27,<3.0)
Requires-Dist: urllib3 (>=1.26,<2.0)
Project-URL: Documentation, https://github.com/sunnydsouza/notion-api-py/blob/main/README.md
Project-URL: Repository, https://github.com/sunnydsouza/notion-api-py
